django_acs_email/__init__.py
django_acs_email/backend.py
django_acs_email/logger.py
django_acs_email/mime.py
django_acs_email/triple.py
django_acs_email/utils.py
django_acs_email-0.0.4.dist-info/METADATA
django_acs_email-0.0.4.dist-info/WHEEL
django_acs_email-0.0.4.dist-info/top_level.txt
django_acs_email-0.0.4.dist-info/RECORD
